[
  {
    "ACT Symbol": "BURL",
    "Company Name": "Burlington Stores, Inc. Common Stock"
  },
  {
    "ACT Symbol": "BVN",
    "Company Name": "Buenaventura Mining Company Inc."
  },
  {
    "ACT Symbol": "BWA",
    "Company Name": "BorgWarner Inc. Common Stock"
  },
  {
    "ACT Symbol": "BWC",
    "Company Name": "Babcock Common Stock"
  },
  {
    "ACT Symbol": "BWG",
    "Company Name": "Legg Mason BW Global Income Opportunities Fund Inc. Common Stock"
  },
  {
    "ACT Symbol": "BWP",
    "Company Name": "Boardwalk Pipeline Partners LP Common Units"
  },
  {
    "ACT Symbol": "BWS",
    "Company Name": "Brown Shoe Company, Inc. Common Stock"
  },
  {
    "ACT Symbol": "BX",
    "Company Name": "The Blackstone Group L.P. Common Units Representing Limited Partnership Interests"
  },
  {
    "ACT Symbol": "BXC",
    "Company Name": "Bluelinx Holdings Inc. Common Stock"
  },
  {
    "ACT Symbol": "BXE",
    "Company Name": "Bellatrix Exploration Ltd Ordinary Shares (Canada)"
  },
  {
    "ACT Symbol": "BXMT",
    "Company Name": "Blackstone Mortgage Trust, Inc. Common Stock"
  },
  {
    "ACT Symbol": "BXMX",
    "Company Name": "Nuveen S&P 500 Buy"
  },
  {
    "ACT Symbol": "BXP",
    "Company Name": "Boston Properties, Inc. Common Stock"
  }
]